analysis/__init__.py
analysis/base.py
analysis/misc.py
analysis/basic/__init__.py
analysis/basic/features.py
analysis/basic/histogram.py
analysis/basic/psth.py
analysis/models/__init__.py
analysis/models/hmm.py
analysis/spatial/__init__.py
analysis/spatial/abstract_place_fields.py
analysis/spatial/abstract_spatial_tuning.py
analysis/spatial/metrics.py
analysis/spatial/place_fields.py
analysis/spatial/spatial_autocorrelation.py
analysis/spatial/spatial_tuning.py
analysis/temporal/__init__.py
analysis/temporal/correlation.py
core/__init__.py
core/classes.py
core/filters.py
core/helpers.py
core/metadata.py
core/registry.py
event/__init__.py
event/base.py
event/group.py
event/lap.py
event/spatial.py
event/transient.py
experiment/__init__.py
experiment/_pairing.py
experiment/base.py
experiment/convert.py
experiment/database.py
experiment/decorators.py
experiment/eeg.py
experiment/group.py
experiment/spatial.py
experiment/utils.py
experiment/virtual.py
experiment/io/__init__.py
experiment/io/basic.py
experiment/io/neurodata.py
extraction/__init__.py
extraction/cnmf/AROIs.py
extraction/cnmf/__init__.py
extraction/cnmf/base.py
extraction/cnmf/convertToMemmap.py
extraction/cnmf/extract_signals.py
extraction/cnmf/import_signals.py
extraction/crossreg/__init__.py
extraction/crossreg/cross_registration.py
extraction/crossreg/utils.py
extraction/denoising/__init__.py
extraction/denoising/base.py
extraction/denoising/convertToMemmap.py
extraction/denoising/trefide_denoiser.py
extraction/manual/__init__.py
extraction/red_identification/__init__.py
extraction/red_identification/base.py
extraction/s2p/__init__.py
extraction/s2p/base.py
extraction/s2p/batch.py
extraction/s2p/extract_signals.py
extraction/s2p/import_signals.py
extraction/s2p/settings.py
filters/__init__.py
filters/joint_filters.py
filters/roi_filters.py
filters/time_filters.py
filters/trial_filters.py
metadata/__init__.py
metadata/base.py
misc/__init__.py
misc/import_imagej_rois.py
misc/level_accessor.py
lab3-0.0.0.dist-info/METADATA
lab3-0.0.0.dist-info/WHEEL
lab3-0.0.0.dist-info/top_level.txt
lab3-0.0.0.dist-info/RECORD
