Metadata-Version: 2.1
Name: lab3
Version: 0.0.0
Summary: Calcium Imaging and Behavior Analysis
Author: Turi et al.
Author-email: gt22553@cumc.columbia.edu
Classifier: Development Status :: 3 - Alpha
Classifier: Programming Language :: Python :: 3.7
Classifier: License :: OSI Approved :: GNU General Public License v3 (GPLv3)
Classifier: Operating System :: OS Independent
Requires-Python: >=3.7
Requires-Dist: cython
Requires-Dist: numpy
Requires-Dist: pandas
Requires-Dist: scikit-learn
Requires-Dist: seaborn
Requires-Dist: h5py
